Workbook

Sheet SAA with CME
A1: SIX Asset Portfolio
B3: Correl | C3: US Large Cap | D3: Dev ex US | E3: EM | F3: UST | G3: US IG Corp Bond | H3: REITs
B4: US Large Cap | C4: 1 | D4: 0.899 | E4: 0.71095 | F4: -0.3458515 | G4: 0.26705 | H4: 0.6438
B5: Dev ex US | C5: 0.899 | D5: 1 | E5: 0.8227 | F5: -0.319864 | G5: 0.38375 | H5: 0.6532
B6: EM | C6: 0.71095 | D6: 0.8227 | E6: 1 | F6: -0.2530505 | G6: 0.4127 | H6: 0.6051
B7: UST | C7: -0.3458515 | D7: -0.319864 | E7: -0.2530505 | F7: 1 | G7: 0.5043 | H7: -0.0238854
B8: US IG Corp Bond | C8: 0.26705 | D8: 0.38375 | E8: 0.4127 | F8: 0.5043 | G8: 1 | H8: 0.4518
B9: REITs | C9: 0.6438 | D9: 0.6532 | E9: 0.6051 | F9: -0.0238854 | G9: 0.4518 | H9: 1
B11: E Return | C11: 0.070929 | D11: 0.0742635 | E11: 0.100071 | F11: 0.0233955 | G11: 0.0367605 | H11: 0.067356
B12: Volatility | C12: 0.193072 | D12: 0.2187735 | E12: 0.3240215 | F12: 0.1215115 | G12: 0.0789305 | H12: 0.276177
J15: Define portfolio objectives and constraints
C16: =C3 -> US Large Cap | D16: =D3 -> Dev ex US | E16: =E3 -> EM | F16: =F3 -> UST | G16: =G3 -> US IG Corp Bond | H16: =H3 -> REITs
B17: Weights | C17: 0.32957596 | D17: 0.1 | E17: 0.17145983 | F17: 0.19896421 | G17: 0.1 | H17: 0.1 | I17: =SUM(C17:H17) -> 1 | J17: Constraint | K17: 0.1 | L17: per asset
B18: E Return | C18: =C17*C11 -> 0.023376494 | D18: =D17*D11 -> 0.00742635 | E18: =E17*E11 -> 0.017158157 | F18: =F17*F11 -> 0.0046548671 | G18: =G17*G11 -> 0.00367605 | H18: =H17*H11 -> 0.0067356 | I18: =SUM(C18:H18) -> 0.063027517 | J18: Objective: Max Return
H19: Variance | I19: {=MMULT(MMULT(C17:H17*$C$12:$H$12,$C$4:$H$9),TRANSPOSE(C17:H17*$C$12:$H$12))} -> 0.022500255
H20: Volatility | I20: =SQRT(I19) -> 0.15000085 | J20: For Risk Level: Medium | K20: 0.15
H21: Risk-Free Rate | I21: 0.03
H22: Sharpe Ratio | I22: =(I18-I21)/I20 -> 0.2201822

Sheet Index Returns
A1: Index | B1: US Large Cap | C1: Dev ex US | D1: EM | E1: UST | F1: US IG Corp Bond | G1: REITs
A2: 43131 | B2: 0.045290404 | C2: 0.048460329 | D2: 0.048309271 | E2: 0.075104782 | F2: -0.002387201 | G2: -0.007527981
A3: 43159 | B3: -0.031242142 | C3: -0.037155504 | D3: -0.037099726 | E3: 0.10615524 | F3: -0.01724575 | G3: -0.052868836
A4: 43189 | B4: 0.0024902994 | C4: -0.011658812 | D4: -0.011562314 | E4: -0.0057899502 | F4: -0.0047781986 | G4: 0.0068646035
A5: 43220 | B5: -0.017096681 | C5: 0.0065936006 | D5: 0.0065547411 | E5: 0.0094362205 | F5: 0.00055783422 | G5: 0.010842502
A6: 43251 | B6: 0.019928038 | C6: 0.0066551801 | D6: 0.0065589384 | E6: 0.03809975 | F6: -0.0076891471 | G6: 0.021958016
A7: 43280 | B7: 0.022670781 | C7: -0.021363402 | D7: -0.021215148 | E7: -0.022114009 | F7: 0.0011626139 | G7: 0.025790931
A8: 43312 | B8: 0.012717833 | C8: -0.015943986 | D8: -0.016116084 | E8: -0.008055036 | F8: 0.0065594835 | G8: 0.016301113
A9: 43343 | B9: 0.021460485 | C9: -0.0059675165 | D9: -0.0059579311 | E9: 2.8502017e-05 | F9: 0.006483612 | G9: 0.013213227
A10: 43371 | B10: 0.014283861 | C10: -0.0031860775 | D10: -0.0031854364 | E10: 0.039991414 | F10: -0.0032318034 | G10: -0.0058463042
A11: 43404 | B11: -0.046754409 | C11: -0.050317546 | D11: -0.049963408 | E11: 0.049048328 | F11: -0.0080948278 | G11: -0.037030481
A12: 43434 | B12: -0.02311175 | C12: -0.024771692 | D12: -0.024968689 | E12: -0.011236614 | F12: -0.0054872829 | G12: 0.020315233
A13: 43465 | B13: -0.053332589 | C13: -0.048228645 | D13: -0.048228645 | E13: -0.091012492 | F13: 0.00877795 | G13: -0.018912625
... A70: 45198 | B70: -0.012104703 | C70: -0.015910618 | D70: -0.015755778 | E70: 0.050546038 | F70: -0.0058931611 | G70: -0.023630311

Sheet SAAPortfolioPerformance
A1: Risk Assessment and Performance Metrics
A3: Ending Date | B3: =TAAPortfolioPerformance!B4 -> 43555
A5: Annual Portfolio Return | B5: =(1+AVERAGEIFS(H17:H85,A17:A85,"<="&B3))^12-1 -> 0.018860416
A6: Compounded Annual Portfolio Return | B6: {=GEOMEAN(IF((A17:A85<=B3), (1+H17:H85)))^12-1} -> 0.016064598
A7: Annual Volatility of Portfolio | B7: {=_xlfn.STDEV.S(IF((A17:A85<=B3),H17:H85))*SQRT(12)} -> 0.076654407
A8: Risk-Free Rate | B8: 0.0235
A9: Sharpe Ratio | B9: =(B5-B8)/B7 -> -0.060525996
A11: Minimum Acceptable Return (MAR) | B11: =B8 -> 0.0235
A12: Target Semi-Standard Deviation | B12: =SQRT(SUMIFS(I17:I85,A17:A85,"<="&B3)/COUNTIFS(A17:A85,"<="&B3,A17:A85,"<="&B3)) -> 0.030087472
A13: Sortino Ratio | B13: =(B5-B11)/B12 -> -0.1542032
I15: Sortino Ratio
A16: Index | B16: US Large Cap | C16: Dev ex US | D16: EM | E16: UST | F16: US IG Corp Bond | G16: REITs | H16: Portfolio Return | I16: min(rp-rT, 0)^2
A17: 43131 | B17: =IF(A17>$B$3,"",'Index Returns'!B2*'SAA with CME'!C$17) -> 0.014926629 | C17: =IF(B17>$B$3,"",'Index Returns'!C2*'SAA with CME'!D$17) -> 0.0048460329 | D17: =IF(C17>$B$3,"",'Index Returns'!D2*'SAA with CME'!E$17) -> 0.0082830993 | E17: =IF(D17>$B$3,"",'Index Returns'!E2*'SAA with CME'!F$17) -> 0.014943163 | F17: =IF(E17>$B$3,"",'Index Returns'!F2*'SAA with CME'!G$17) -> -0.0002387201 | G17: =IF(F17>$B$3,"",'Index Returns'!G2*'SAA with CME'!H$17) -> -0.0007527981 | H17: =IF(A17>$B$3,"",SUM(B17:G17)) -> 0.042007406 | I17: =IF(A17>$B$3,"",(MIN(H17-$B$11,0)^2)) -> 0
A18: 43159 | B18: =IF(A18>$B$3,"",'Index Returns'!B3*'SAA with CME'!C$17) -> -0.010296659 | C18: =IF(B18>$B$3,"",'Index Returns'!C3*'SAA with CME'!D$17) -> -0.0037155504 | D18: =IF(C18>$B$3,"",'Index Returns'!D3*'SAA with CME'!E$17) -> -0.0063611126 | E18: =IF(D18>$B$3,"",'Index Returns'!E3*'SAA with CME'!F$17) -> 0.021121093 | F18: =IF(E18>$B$3,"",'Index Returns'!F3*'SAA with CME'!G$17) -> -0.001724575 | G18: =IF(F18>$B$3,"",'Index Returns'!G3*'SAA with CME'!H$17) -> -0.0052868836 | H18: =IF(A18>$B$3,"",SUM(B18:G18)) -> -0.0062636879 | I18: =IF(A18>$B$3,"",(MIN(H18-$B$11,0)^2)) -> 0.00088587712
A19: 43189 | B19: =IF(A19>$B$3,"",'Index Returns'!B4*'SAA with CME'!C$17) -> 0.00082074284 | C19: =IF(B19>$B$3,"",'Index Returns'!C4*'SAA with CME'!D$17) -> -0.0011658812 | D19: =IF(C19>$B$3,"",'Index Returns'!D4*'SAA with CME'!E$17) -> -0.0019824724 | E19: =IF(D19>$B$3,"",'Index Returns'!E4*'SAA with CME'!F$17) -> -0.0011519928 | F19: =IF(E19>$B$3,"",'Index Returns'!F4*'SAA with CME'!G$17) -> -0.00047781986 | G19: =IF(F19>$B$3,"",'Index Returns'!G4*'SAA with CME'!H$17) -> 0.00068646035 | H19: =IF(A19>$B$3,"",SUM(B19:G19)) -> -0.0032709632 | I19: =IF(A19>$B$3,"",(MIN(H19-$B$11,0)^2)) -> 0.00071668447
A20: 43220 | B20: =IF(A20>$B$3,"",'Index Returns'!B5*'SAA with CME'!C$17) -> -0.005634655 | C20: =IF(B20>$B$3,"",'Index Returns'!C5*'SAA with CME'!D$17) -> 0.00065936006 | D20: =IF(C20>$B$3,"",'Index Returns'!D5*'SAA with CME'!E$17) -> 0.0011238748 | E20: =IF(D20>$B$3,"",'Index Returns'!E5*'SAA with CME'!F$17) -> 0.0018774701 | F20: =IF(E20>$B$3,"",'Index Returns'!F5*'SAA with CME'!G$17) -> 5.5783422e-05 | G20: =IF(F20>$B$3,"",'Index Returns'!G5*'SAA with CME'!H$17) -> 0.0010842502 | H20: =IF(A20>$B$3,"",SUM(B20:G20)) -> -0.00083391642 | I20: =IF(A20>$B$3,"",(MIN(H20-$B$11,0)^2)) -> 0.00059213949
A21: 43251 | B21: =IF(A21>$B$3,"",'Index Returns'!B6*'SAA with CME'!C$17) -> 0.0065678023 | C21: =IF(B21>$B$3,"",'Index Returns'!C6*'SAA with CME'!D$17) -> 0.00066551801 | D21: =IF(C21>$B$3,"",'Index Returns'!D6*'SAA with CME'!E$17) -> 0.0011245945 | E21: =IF(D21>$B$3,"",'Index Returns'!E6*'SAA with CME'!F$17) -> 0.0075804864 | F21: =IF(E21>$B$3,"",'Index Returns'!F6*'SAA with CME'!G$17) -> -0.00076891471 | G21: =IF(F21>$B$3,"",'Index Returns'!G6*'SAA with CME'!H$17) -> 0.0021958016 | H21: =IF(A21>$B$3,"",SUM(B21:G21)) -> 0.017365288 | I21: =IF(A21>$B$3,"",(MIN(H21-$B$11,0)^2)) -> 3.763469e-05
A22: 43280 | B22: =IF(A22>$B$3,"",'Index Returns'!B7*'SAA with CME'!C$17) -> 0.0074717445 | C22: =IF(B22>$B$3,"",'Index Returns'!C7*'SAA with CME'!D$17) -> -0.0021363402 | D22: =IF(C22>$B$3,"",'Index Returns'!D7*'SAA with CME'!E$17) -> -0.0036375457 | E22: =IF(D22>$B$3,"",'Index Returns'!E7*'SAA with CME'!F$17) -> -0.0043998962 | F22: =IF(E22>$B$3,"",'Index Returns'!F7*'SAA with CME'!G$17) -> 0.00011626139 | G22: =IF(F22>$B$3,"",'Index Returns'!G7*'SAA with CME'!H$17) -> 0.0025790931 | H22: =IF(A22>$B$3,"",SUM(B22:G22)) -> -6.6831488e-06 | I22: =IF(A22>$B$3,"",(MIN(H22-$B$11,0)^2)) -> 0.00055256415
A23: 43312 | B23: =IF(A23>$B$3,"",'Index Returns'!B8*'SAA with CME'!C$17) -> 0.0041914921 | C23: =IF(B23>$B$3,"",'Index Returns'!C8*'SAA with CME'!D$17) -> -0.0015943986 | D23: =IF(C23>$B$3,"",'Index Returns'!D8*'SAA with CME'!E$17) -> -0.002763261 | E23: =IF(D23>$B$3,"",'Index Returns'!E8*'SAA with CME'!F$17) -> -0.0016026638 | F23: =IF(E23>$B$3,"",'Index Returns'!F8*'SAA with CME'!G$17) -> 0.00065594835 | G23: =IF(F23>$B$3,"",'Index Returns'!G8*'SAA with CME'!H$17) -> 0.0016301113 | H23: =IF(A23>$B$3,"",SUM(B23:G23)) -> 0.00051722835 | I23: =IF(A23>$B$3,"",(MIN(H23-$B$11,0)^2)) -> 0.00052820779
A24: 43343 | B24: =IF(A24>$B$3,"",'Index Returns'!B9*'SAA with CME'!C$17) -> 0.0070728602 | C24: =IF(B24>$B$3,"",'Index Returns'!C9*'SAA with CME'!D$17) -> -0.00059675165 | D24: =IF(C24>$B$3,"",'Index Returns'!D9*'SAA with CME'!E$17) -> -0.0010215458 | E24: =IF(D24>$B$3,"",'Index Returns'!E9*'SAA with CME'!F$17) -> 5.6708813e-06 | F24: =IF(E24>$B$3,"",'Index Returns'!F9*'SAA with CME'!G$17) -> 0.0006483612 | G24: =IF(F24>$B$3,"",'Index Returns'!G9*'SAA with CME'!H$17) -> 0.0013213227 | H24: =IF(A24>$B$3,"",SUM(B24:G24)) -> 0.0074299174 | I24: =IF(A24>$B$3,"",(MIN(H24-$B$11,0)^2)) -> 0.00025824755
A25: 43371 | B25: =IF(A25>$B$3,"",'Index Returns'!B10*'SAA with CME'!C$17) -> 0.0047076171 | C25: =IF(B25>$B$3,"",'Index Returns'!C10*'SAA with CME'!D$17) -> -0.00031860775 | D25: =IF(C25>$B$3,"",'Index Returns'!D10*'SAA with CME'!E$17) -> -0.00054617438 | E25: =IF(D25>$B$3,"",'Index Returns'!E10*'SAA with CME'!F$17) -> 0.00795686 | F25: =IF(E25>$B$3,"",'Index Returns'!F10*'SAA with CME'!G$17) -> -0.00032318034 | G25: =IF(F25>$B$3,"",'Index Returns'!G10*'SAA with CME'!H$17) -> -0.00058463042 | H25: =IF(A25>$B$3,"",SUM(B25:G25)) -> 0.010891884 | I25: =IF(A25>$B$3,"",(MIN(H25-$B$11,0)^2)) -> 0.00015896458
A26: 43404 | B26: =IF(A26>$B$3,"",'Index Returns'!B11*'SAA with CME'!C$17) -> -0.015409129 | C26: =IF(B26>$B$3,"",'Index Returns'!C11*'SAA with CME'!D$17) -> -0.0050317546 | D26: =IF(C26>$B$3,"",'Index Returns'!D11*'SAA with CME'!E$17) -> -0.0085667173 | E26: =IF(D26>$B$3,"",'Index Returns'!E11*'SAA with CME'!F$17) -> 0.0097588616 | F26: =IF(E26>$B$3,"",'Index Returns'!F11*'SAA with CME'!G$17) -> -0.00080948278 | G26: =IF(F26>$B$3,"",'Index Returns'!G11*'SAA with CME'!H$17) -> -0.0037030481 | H26: =IF(A26>$B$3,"",SUM(B26:G26)) -> -0.023761271 | I26: =IF(A26>$B$3,"",(MIN(H26-$B$11,0)^2)) -> 0.0022336277
A27: 43434 | B27: =IF(A27>$B$3,"",'Index Returns'!B12*'SAA with CME'!C$17) -> -0.0076170774 | C27: =IF(B27>$B$3,"",'Index Returns'!C12*'SAA with CME'!D$17) -> -0.0024771692 | D27: =IF(C27>$B$3,"",'Index Returns'!D12*'SAA with CME'!E$17) -> -0.0042811271 | E27: =IF(D27>$B$3,"",'Index Returns'!E12*'SAA with CME'!F$17) -> -0.002235684 | F27: =IF(E27>$B$3,"",'Index Returns'!F12*'SAA with CME'!G$17) -> -0.00054872829 | G27: =IF(F27>$B$3,"",'Index Returns'!G12*'SAA with CME'!H$17) -> 0.0020315233 | H27: =IF(A27>$B$3,"",SUM(B27:G27)) -> -0.015128263 | I27: =IF(A27>$B$3,"",(MIN(H27-$B$11,0)^2)) -> 0.0014921427
A28: 43465 | B28: =IF(A28>$B$3,"",'Index Returns'!B13*'SAA with CME'!C$17) -> -0.01757714 | C28: =IF(B28>$B$3,"",'Index Returns'!C13*'SAA with CME'!D$17) -> -0.0048228645 | D28: =IF(C28>$B$3,"",'Index Returns'!D13*'SAA with CME'!E$17) -> -0.0082692752 | E28: =IF(D28>$B$3,"",'Index Returns'!E13*'SAA with CME'!F$17) -> -0.018108228 | F28: =IF(E28>$B$3,"",'Index Returns'!F13*'SAA with CME'!G$17) -> 0.000877795 | G28: =IF(F28>$B$3,"",'Index Returns'!G13*'SAA with CME'!H$17) -> -0.0018912625 | H28: =IF(A28>$B$3,"",SUM(B28:G28)) -> -0.049790975 | I28: =IF(A28>$B$3,"",(MIN(H28-$B$11,0)^2)) -> 0.005371567
... A85: 45198 | B85: =IF(A85>$B$3,"",'Index Returns'!B70*'SAA with CME'!C$17) | C85: =IF(B85>$B$3,"",'Index Returns'!C70*'SAA with CME'!D$17) | D85: =IF(C85>$B$3,"",'Index Returns'!D70*'SAA with CME'!E$17) | E85: =IF(D85>$B$3,"",'Index Returns'!E70*'SAA with CME'!F$17) | F85: =IF(E85>$B$3,"",'Index Returns'!F70*'SAA with CME'!G$17) | G85: =IF(F85>$B$3,"",'Index Returns'!G70*'SAA with CME'!H$17) | H85: =IF(A85>$B$3,"",SUM(B85:G85)) | I85: =IF(A85>$B$3,"",(MIN(H85-$B$11,0)^2))

Sheet TAA
A1: Strategic vs Tactical Weight
C2: Row #
A3: Select a Historic Starting Date | B3: 43371 | C3: =MATCH(B3,'Index Returns'!A:A,1) -> 10
A4: Select a Historic Ending Date | B4: 43465 | C4: =MATCH(B4,'Index Returns'!A:A,1) -> 13
C6: US Large Cap | D6: Dev ex US | E6: EM | F6: UST | G6: US IG Corp Bond | H6: REITs
B7: Correl | C7: =MATCH(C6,'Index Returns'!$B$1:$G$1,0) -> 1 | D7: =MATCH(D6,'Index Returns'!$B$1:$G$1,0) -> 2 | E7: =MATCH(E6,'Index Returns'!$B$1:$G$1,0) -> 3 | F7: =MATCH(F6,'Index Returns'!$B$1:$G$1,0) -> 4 | G7: =MATCH(G6,'Index Returns'!$B$1:$G$1,0) -> 5 | H7: =MATCH(H6,'Index Returns'!$B$1:$G$1,0) -> 6
A8: US Large Cap | B8: =MATCH(A8,'Index Returns'!$B$1:$G$1,0) -> 1 | C8: =CORREL(OFFSET(INDIRECT("'Index Returns'!$A$"&TAA!$C$3&":$A$"&TAA!$C$4),0,TAA!C$7),OFFSET(INDIRECT("'Index Returns'!$A$"&TAA!$C$3&":$A$"&TAA!$C$4),0,TAA!$B8)) -> 1 | D8: =CORREL(OFFSET(INDIRECT("'Index Returns'!$A$"&TAA!$C$3&":$A$"&TAA!$C$4),0,TAA!D$7),OFFSET(INDIRECT("'Index Returns'!$A$"&TAA!$C$3&":$A$"&TAA!$C$4),0,TAA!$B8)) -> 0.9852162 | E8: =CORREL(OFFSET(INDIRECT("'Index Returns'!$A$"&TAA!$C$3&":$A$"&TAA!$C$4),0,TAA!E$7),OFFSET(INDIRECT("'Index Returns'!$A$"&TAA!$C$3&":$A$"&TAA!$C$4),0,TAA!$B8)) -> 0.98669661 | F8: =CORREL(OFFSET(INDIRECT("'Index Returns'!$A$"&TAA!$C$3&":$A$"&TAA!$C$4),0,TAA!F$7),OFFSET(INDIRECT("'Index Returns'!$A$"&TAA!$C$3&":$A$"&TAA!$C$4),0,TAA!$B8)) -> 0.51489359 | G8: =CORREL(OFFSET(INDIRECT("'Index Returns'!$A$"&TAA!$C$3&":$A$"&TAA!$C$4),0,TAA!G$7),OFFSET(INDIRECT("'Index Returns'!$A$"&TAA!$C$3&":$A$"&TAA!$C$4),0,TAA!$B8)) -> -0.33301793 | H8: =CORREL(OFFSET(INDIRECT("'Index Returns'!$A$"&TAA!$C$3&":$A$"&TAA!$C$4),0,TAA!H$7),OFFSET(INDIRECT("'Index Returns'!$A$"&TAA!$C$3&":$A$"&TAA!$C$4),0,TAA!$B8)) -> 0.47813672
A9: Dev ex US | B9: =MATCH(A9,'Index Returns'!$B$1:$G$1,0) -> 2 | C9: =CORREL(OFFSET(INDIRECT("'Index Returns'!$A$"&TAA!$C$3&":$A$"&TAA!$C$4),0,TAA!C$7),OFFSET(INDIRECT("'Index Returns'!$A$"&TAA!$C$3&":$A$"&TAA!$C$4),0,TAA!$B9)) -> 0.9852162 | D9: =CORREL(OFFSET(INDIRECT("'Index Returns'!$A$"&TAA!$C$3&":$A$"&TAA!$C$4),0,TAA!D$7),OFFSET(INDIRECT("'Index Returns'!$A$"&TAA!$C$3&":$A$"&TAA!$C$4),0,TAA!$B9)) -> 1 | E9: =CORREL(OFFSET(INDIRECT("'Index Returns'!$A$"&TAA!$C$3&":$A$"&TAA!$C$4),0,TAA!E$7),OFFSET(INDIRECT("'Index Returns'!$A$"&TAA!$C$3&":$A$"&TAA!$C$4),0,TAA!$B9)) -> 0.99996065 | F9: =CORREL(OFFSET(INDIRECT("'Index Returns'!$A$"&TAA!$C$3&":$A$"&TAA!$C$4),0,TAA!F$7),OFFSET(INDIRECT("'Index Returns'!$A$"&TAA!$C$3&":$A$"&TAA!$C$4),0,TAA!$B9)) -> 0.38657729 | G9: =CORREL(OFFSET(INDIRECT("'Index Returns'!$A$"&TAA!$C$3&":$A$"&TAA!$C$4),0,TAA!G$7),OFFSET(INDIRECT("'Index Returns'!$A$"&TAA!$C$3&":$A$"&TAA!$C$4),0,TAA!$B9)) -> -0.24927021 | H9: =CORREL(OFFSET(INDIRECT("'Index Returns'!$A$"&TAA!$C$3&":$A$"&TAA!$C$4),0,TAA!H$7),OFFSET(INDIRECT("'Index Returns'!$A$"&TAA!$C$3&":$A$"&TAA!$C$4),0,TAA!$B9)) -> 0.60896441
A10: EM | B10: =MATCH(A10,'Index Returns'!$B$1:$G$1,0) -> 3 | C10: =CORREL(OFFSET(INDIRECT("'Index Returns'!$A$"&TAA!$C$3&":$A$"&TAA!$C$4),0,TAA!C$7),OFFSET(INDIRECT("'Index Returns'!$A$"&TAA!$C$3&":$A$"&TAA!$C$4),0,TAA!$B10)) -> 0.98669661 | D10: =CORREL(OFFSET(INDIRECT("'Index Returns'!$A$"&TAA!$C$3&":$A$"&TAA!$C$4),0,TAA!D$7),OFFSET(INDIRECT("'Index Returns'!$A$"&TAA!$C$3&":$A$"&TAA!$C$4),0,TAA!$B10)) -> 0.99996065 | E10: =CORREL(OFFSET(INDIRECT("'Index Returns'!$A$"&TAA!$C$3&":$A$"&TAA!$C$4),0,TAA!E$7),OFFSET(INDIRECT("'Index Returns'!$A$"&TAA!$C$3&":$A$"&TAA!$C$4),0,TAA!$B10)) -> 1 | F10: =CORREL(OFFSET(INDIRECT("'Index Returns'!$A$"&TAA!$C$3&":$A$"&TAA!$C$4),0,TAA!F$7),OFFSET(INDIRECT("'Index Returns'!$A$"&TAA!$C$3&":$A$"&TAA!$C$4),0,TAA!$B10)) -> 0.39337735 | G10: =CORREL(OFFSET(INDIRECT("'Index Returns'!$A$"&TAA!$C$3&":$A$"&TAA!$C$4),0,TAA!G$7),OFFSET(INDIRECT("'Index Returns'!$A$"&TAA!$C$3&":$A$"&TAA!$C$4),0,TAA!$B10)) -> -0.25357961 | H10: =CORREL(OFFSET(INDIRECT("'Index Returns'!$A$"&TAA!$C$3&":$A$"&TAA!$C$4),0,TAA!H$7),OFFSET(INDIRECT("'Index Returns'!$A$"&TAA!$C$3&":$A$"&TAA!$C$4),0,TAA!$B10)) -> 0.60254628
A11: UST | B11: =MATCH(A11,'Index Returns'!$B$1:$G$1,0) -> 4 | C11: =CORREL(OFFSET(INDIRECT("'Index Returns'!$A$"&TAA!$C$3&":$A$"&TAA!$C$4),0,TAA!C$7),OFFSET(INDIRECT("'Index Returns'!$A$"&TAA!$C$3&":$A$"&TAA!$C$4),0,TAA!$B11)) -> 0.51489359 | D11: =CORREL(OFFSET(INDIRECT("'Index Returns'!$A$"&TAA!$C$3&":$A$"&TAA!$C$4),0,TAA!D$7),OFFSET(INDIRECT("'Index Returns'!$A$"&TAA!$C$3&":$A$"&TAA!$C$4),0,TAA!$B11)) -> 0.38657729 | E11: =CORREL(OFFSET(INDIRECT("'Index Returns'!$A$"&TAA!$C$3&":$A$"&TAA!$C$4),0,TAA!E$7),OFFSET(INDIRECT("'Index Returns'!$A$"&TAA!$C$3&":$A$"&TAA!$C$4),0,TAA!$B11)) -> 0.39337735 | F11: =CORREL(OFFSET(INDIRECT("'Index Returns'!$A$"&TAA!$C$3&":$A$"&TAA!$C$4),0,TAA!F$7),OFFSET(INDIRECT("'Index Returns'!$A$"&TAA!$C$3&":$A$"&TAA!$C$4),0,TAA!$B11)) -> 1 | G11: =CORREL(OFFSET(INDIRECT("'Index Returns'!$A$"&TAA!$C$3&":$A$"&TAA!$C$4),0,TAA!G$7),OFFSET(INDIRECT("'Index Returns'!$A$"&TAA!$C$3&":$A$"&TAA!$C$4),0,TAA!$B11)) -> -0.89756363 | H11: =CORREL(OFFSET(INDIRECT("'Index Returns'!$A$"&TAA!$C$3&":$A$"&TAA!$C$4),0,TAA!H$7),OFFSET(INDIRECT("'Index Returns'!$A$"&TAA!$C$3&":$A$"&TAA!$C$4),0,TAA!$B11)) -> -0.1493422
A12: US IG Corp Bond | B12: =MATCH(A12,'Index Returns'!$B$1:$G$1,0) -> 5 | C12: =CORREL(OFFSET(INDIRECT("'Index Returns'!$A$"&TAA!$C$3&":$A$"&TAA!$C$4),0,TAA!C$7),OFFSET(INDIRECT("'Index Returns'!$A$"&TAA!$C$3&":$A$"&TAA!$C$4),0,TAA!$B12)) -> -0.33301793 | D12: =CORREL(OFFSET(INDIRECT("'Index Returns'!$A$"&TAA!$C$3&":$A$"&TAA!$C$4),0,TAA!D$7),OFFSET(INDIRECT("'Index Returns'!$A$"&TAA!$C$3&":$A$"&TAA!$C$4),0,TAA!$B12)) -> -0.24927021 | E12: =CORREL(OFFSET(INDIRECT("'Index Returns'!$A$"&TAA!$C$3&":$A$"&TAA!$C$4),0,TAA!E$7),OFFSET(INDIRECT("'Index Returns'!$A$"&TAA!$C$3&":$A$"&TAA!$C$4),0,TAA!$B12)) -> -0.25357961 | F12: =CORREL(OFFSET(INDIRECT("'Index Returns'!$A$"&TAA!$C$3&":$A$"&TAA!$C$4),0,TAA!F$7),OFFSET(INDIRECT("'Index Returns'!$A$"&TAA!$C$3&":$A$"&TAA!$C$4),0,TAA!$B12)) -> -0.89756363 | G12: =CORREL(OFFSET(INDIRECT("'Index Returns'!$A$"&TAA!$C$3&":$A$"&TAA!$C$4),0,TAA!G$7),OFFSET(INDIRECT("'Index Returns'!$A$"&TAA!$C$3&":$A$"&TAA!$C$4),0,TAA!$B12)) -> 1 | H12: =CORREL(OFFSET(INDIRECT("'Index Returns'!$A$"&TAA!$C$3&":$A$"&TAA!$C$4),0,TAA!H$7),OFFSET(INDIRECT("'Index Returns'!$A$"&TAA!$C$3&":$A$"&TAA!$C$4),0,TAA!$B12)) -> -0.078085724
A13: REITs | B13: =MATCH(A13,'Index Returns'!$B$1:$G$1,0) -> 6 | C13: =CORREL(OFFSET(INDIRECT("'Index Returns'!$A$"&TAA!$C$3&":$A$"&TAA!$C$4),0,TAA!C$7),OFFSET(INDIRECT("'Index Returns'!$A$"&TAA!$C$3&":$A$"&TAA!$C$4),0,TAA!$B13)) -> 0.47813672 | D13: =CORREL(OFFSET(INDIRECT("'Index Returns'!$A$"&TAA!$C$3&":$A$"&TAA!$C$4),0,TAA!D$7),OFFSET(INDIRECT("'Index Returns'!$A$"&TAA!$C$3&":$A$"&TAA!$C$4),0,TAA!$B13)) -> 0.60896441 | E13: =CORREL(OFFSET(INDIRECT("'Index Returns'!$A$"&TAA!$C$3&":$A$"&TAA!$C$4),0,TAA!E$7),OFFSET(INDIRECT("'Index Returns'!$A$"&TAA!$C$3&":$A$"&TAA!$C$4),0,TAA!$B13)) -> 0.60254628 | F13: =CORREL(OFFSET(INDIRECT("'Index Returns'!$A$"&TAA!$C$3&":$A$"&TAA!$C$4),0,TAA!F$7),OFFSET(INDIRECT("'Index Returns'!$A$"&TAA!$C$3&":$A$"&TAA!$C$4),0,TAA!$B13)) -> -0.1493422 | G13: =CORREL(OFFSET(INDIRECT("'Index Returns'!$A$"&TAA!$C$3&":$A$"&TAA!$C$4),0,TAA!G$7),OFFSET(INDIRECT("'Index Returns'!$A$"&TAA!$C$3&":$A$"&TAA!$C$4),0,TAA!$B13)) -> -0.078085724 | H13: =CORREL(OFFSET(INDIRECT("'Index Returns'!$A$"&TAA!$C$3&":$A$"&TAA!$C$4),0,TAA!H$7),OFFSET(INDIRECT("'Index Returns'!$A$"&TAA!$C$3&":$A$"&TAA!$C$4),0,TAA!$B13)) -> 1
B15: E Return | C15: =(1+AVERAGEIFS('Index Returns'!B2:B70,'Index Returns'!$A$2:$A$70,">="&$B$3,'Index Returns'!$A$2:$A$70,"<="&$B$4))^12-1 -> -0.28199268 | D15: =(1+AVERAGEIFS('Index Returns'!C2:C70,'Index Returns'!$A$2:$A$70,">="&$B$3,'Index Returns'!$A$2:$A$70,"<="&$B$4))^12-1 -> -0.31998655 | E15: =(1+AVERAGEIFS('Index Returns'!D2:D70,'Index Returns'!$A$2:$A$70,">="&$B$3,'Index Returns'!$A$2:$A$70,"<="&$B$4))^12-1 -> -0.31965408 | F15: =(1+AVERAGEIFS('Index Returns'!E2:E70,'Index Returns'!$A$2:$A$70,">="&$B$3,'Index Returns'!$A$2:$A$70,"<="&$B$4))^12-1 -> -0.038916197 | G15: =(1+AVERAGEIFS('Index Returns'!F2:F70,'Index Returns'!$A$2:$A$70,">="&$B$3,'Index Returns'!$A$2:$A$70,"<="&$B$4))^12-1 -> -0.023843289 | H15: =(1+AVERAGEIFS('Index Returns'!G2:G70,'Index Returns'!$A$2:$A$70,">="&$B$3,'Index Returns'!$A$2:$A$70,"<="&$B$4))^12-1 -> -0.1175667
B16: Volatility | C16: {=_xlfn.STDEV.S(IF(('Index Returns'!$A$2:$A$70>=$B$3)*('Index Returns'!$A$2:$A70<=$B$4),'Index Returns'!B2:B70))*SQRT(12)} -> 0.105885 | D16: {=_xlfn.STDEV.S(IF(('Index Returns'!$A$2:$A$70>=$B$3)*('Index Returns'!$A$2:$A70<=$B$4),'Index Returns'!C2:C70))*SQRT(12)} -> 0.076963171 | E16: {=_xlfn.STDEV.S(IF(('Index Returns'!$A$2:$A$70>=$B$3)*('Index Returns'!$A$2:$A70<=$B$4),'Index Returns'!D2:D70))*SQRT(12)} -> 0.076552924 | F16: {=_xlfn.STDEV.S(IF(('Index Returns'!$A$2:$A$70>=$B$3)*('Index Returns'!$A$2:$A70<=$B$4),'Index Returns'!E2:E70))*SQRT(12)} -> 0.22244968 | G16: {=_xlfn.STDEV.S(IF(('Index Returns'!$A$2:$A$70>=$B$3)*('Index Returns'!$A$2:$A70<=$B$4),'Index Returns'!F2:F70))*SQRT(12)} -> 0.025844867 | H16: {=_xlfn.STDEV.S(IF(('Index Returns'!$A$2:$A$70>=$B$3)*('Index Returns'!$A$2:$A70<=$B$4),'Index Returns'!G2:G70))*SQRT(12)} -> 0.083565664
C18: Strategic Weights
C19: =C6 -> US Large Cap | D19: =D6 -> Dev ex US | E19: =E6 -> EM | F19: =F6 -> UST | G19: =G6 -> US IG Corp Bond | H19: =H6 -> REITs
B20: Weights | C20: ='SAA with CME'!C17 -> 0.32957596 | D20: ='SAA with CME'!D17 -> 0.1 | E20: ='SAA with CME'!E17 -> 0.17145983 | F20: ='SAA with CME'!F17 -> 0.19896421 | G20: ='SAA with CME'!G17 -> 0.1 | H20: ='SAA with CME'!H17 -> 0.1
C22: Tactical Weights | J22: Define portfolio objectives and constraints
C23: =C6 -> US Large Cap | D23: =D6 -> Dev ex US | E23: =E6 -> EM | F23: =F6 -> UST | G23: =G6 -> US IG Corp Bond | H23: =H6 -> REITs
B24: Weights | C24: 0.12957596 | D24: 0.1 | E24: 0.1 | F24: 0.27042402 | G24: 0.3 | H24: 0.1 | I24: =SUM(C24:H24) -> 0.99999999 | J24: Constraint | K24: 0.1 | L24: per asset
B25: E Return | C25: =C15*C24 -> -0.036539474 | D25: =D15*D24 -> -0.031998655 | E25: =E15*E24 -> -0.031965408 | F25: =F15*F24 -> -0.010523874 | G25: =G15*G24 -> -0.0071529868 | H25: =H15*H24 -> -0.01175667 | I25: =SUM(C25:H25) -> -0.12993707 | J25: Objective: Max Return
H26: Variance | I26: {=MMULT(MMULT(C24:H24*$C$16:$H$16,$C$8:$H$13),TRANSPOSE(C24:H24*$C$16:$H$16))} -> 0.0052949176
H27: Volatility | I27: =SQRT(I26) -> 0.072766184 | J27: For Risk Level: Medium | K27: 0.15
H28: Risk-Free Rate | I28: 0.0165
H29: Sharpe Ratio | I29: =(I25-I28)/I27 -> -2.012433
B31: Weight Deviation | C31: =C24-C20 -> -0.2 | D31: =D24-D20 -> 0 | E31: =E24-E20 -> -0.071459829 | F31: =F24-F20 -> 0.071459817 | G31: =G24-G20 -> 0.2 | H31: =H24-H20 -> 0

Sheet TAAPortfolioPerformance
A1: Risk Assessment and Performance Metrics with TAA Tilt
A3: TAA Tilt Effects Starting Date | B3: =TAA!B4 -> 43465
A4: Ending Date 1 Quarter Out | B4: =EOMONTH(B3,3) -> 43555
A6: Annual Portfolio Return | B6: =(1+AVERAGEIFS(H18:H86,A18:A86,"<="&B4))^12-1 -> 0.0048304048
A7: Compounded Annual Portfolio Return | B7: {=GEOMEAN(IF((A18:A86<=B4), (1+H18:H86)))^12-1} -> 0.0023521964
A8: Annual Volatility of Portfolio | B8: {=_xlfn.STDEV.S(IF((A18:A86<=B4),H18:H86))*SQRT(12)} -> 0.072531635
A9: Risk-Free Rate | B9: 0.0235
A10: Sharpe Ratio | B10: =(B6-B9)/B8 -> -0.25739934
A12: Minimum Acceptable Return (MAR) | B12: =B9 -> 0.0235
A13: Target Semi-Standard Deviation | B13: =SQRT(SUMIFS(I18:I86,A18:A86,"<="&B4)/COUNTIFS(A18:A86,"<="&B4)) -> 0.030329288
A14: Sortino Ratio | B14: =(B6-B12)/B13 -> -0.61556326
I16: Sortino Ratio
A17: Index | B17: US Large Cap | C17: Dev ex US | D17: EM | E17: UST | F17: US IG Corp Bond | G17: REITs | H17: Portfolio Return | I17: min(rp-rT, 0)^2
A18: 43131 | B18: =IF(A18<=$B$3,'Index Returns'!B2*'SAA with CME'!C$17,IF(TAAPortfolioPerformance!A18>TAAPortfolioPerformance!$B$4,"",'Index Returns'!B2*TAA!C$24)) -> 0.014926629 | C18: =IF(B18<=$B$3,'Index Returns'!C2*'SAA with CME'!D$17,IF(TAAPortfolioPerformance!B18>TAAPortfolioPerformance!$B$4,"",'Index Returns'!C2*TAA!D$24)) -> 0.0048460329 | D18: =IF(C18<=$B$3,'Index Returns'!D2*'SAA with CME'!E$17,IF(TAAPortfolioPerformance!C18>TAAPortfolioPerformance!$B$4,"",'Index Returns'!D2*TAA!E$24)) -> 0.0082830993 | E18: =IF(D18<=$B$3,'Index Returns'!E2*'SAA with CME'!F$17,IF(TAAPortfolioPerformance!D18>TAAPortfolioPerformance!$B$4,"",'Index Returns'!E2*TAA!F$24)) -> 0.014943163 | F18: =IF(E18<=$B$3,'Index Returns'!F2*'SAA with CME'!G$17,IF(TAAPortfolioPerformance!E18>TAAPortfolioPerformance!$B$4,"",'Index Returns'!F2*TAA!G$24)) -> -0.0002387201 | G18: =IF(F18<=$B$3,'Index Returns'!G2*'SAA with CME'!H$17,IF(TAAPortfolioPerformance!F18>TAAPortfolioPerformance!$B$4,"",'Index Returns'!G2*TAA!H$24)) -> -0.0007527981 | H18: =IF(G18="","",SUM(B18:G18)) -> 0.042007406 | I18: =IF(G18="","",(MIN(H18-$B$12,0)^2)) -> 0
A19: 43159 | B19: =IF(A19<=$B$3,'Index Returns'!B3*'SAA with CME'!C$17,IF(TAAPortfolioPerformance!A19>TAAPortfolioPerformance!$B$4,"",'Index Returns'!B3*TAA!C$24)) -> -0.010296659 | C19: =IF(B19<=$B$3,'Index Returns'!C3*'SAA with CME'!D$17,IF(TAAPortfolioPerformance!B19>TAAPortfolioPerformance!$B$4,"",'Index Returns'!C3*TAA!D$24)) -> -0.0037155504 | D19: =IF(C19<=$B$3,'Index Returns'!D3*'SAA with CME'!E$17,IF(TAAPortfolioPerformance!C19>TAAPortfolioPerformance!$B$4,"",'Index Returns'!D3*TAA!E$24)) -> -0.0063611126 | E19: =IF(D19<=$B$3,'Index Returns'!E3*'SAA with CME'!F$17,IF(TAAPortfolioPerformance!D19>TAAPortfolioPerformance!$B$4,"",'Index Returns'!E3*TAA!F$24)) -> 0.021121093 | F19: =IF(E19<=$B$3,'Index Returns'!F3*'SAA with CME'!G$17,IF(TAAPortfolioPerformance!E19>TAAPortfolioPerformance!$B$4,"",'Index Returns'!F3*TAA!G$24)) -> -0.001724575 | G19: =IF(F19<=$B$3,'Index Returns'!G3*'SAA with CME'!H$17,IF(TAAPortfolioPerformance!F19>TAAPortfolioPerformance!$B$4,"",'Index Returns'!G3*TAA!H$24)) -> -0.0052868836 | H19: =IF(G19="","",SUM(B19:G19)) -> -0.0062636879 | I19: =IF(G19="","",(MIN(H19-$B$12,0)^2)) -> 0.00088587712
A20: 43189 | B20: =IF(A20<=$B$3,'Index Returns'!B4*'SAA with CME'!C$17,IF(TAAPortfolioPerformance!A20>TAAPortfolioPerformance!$B$4,"",'Index Returns'!B4*TAA!C$24)) -> 0.00082074284 | C20: =IF(B20<=$B$3,'Index Returns'!C4*'SAA with CME'!D$17,IF(TAAPortfolioPerformance!B20>TAAPortfolioPerformance!$B$4,"",'Index Returns'!C4*TAA!D$24)) -> -0.0011658812 | D20: =IF(C20<=$B$3,'Index Returns'!D4*'SAA with CME'!E$17,IF(TAAPortfolioPerformance!C20>TAAPortfolioPerformance!$B$4,"",'Index Returns'!D4*TAA!E$24)) -> -0.0019824724 | E20: =IF(D20<=$B$3,'Index Returns'!E4*'SAA with CME'!F$17,IF(TAAPortfolioPerformance!D20>TAAPortfolioPerformance!$B$4,"",'Index Returns'!E4*TAA!F$24)) -> -0.0011519928 | F20: =IF(E20<=$B$3,'Index Returns'!F4*'SAA with CME'!G$17,IF(TAAPortfolioPerformance!E20>TAAPortfolioPerformance!$B$4,"",'Index Returns'!F4*TAA!G$24)) -> -0.00047781986 | G20: =IF(F20<=$B$3,'Index Returns'!G4*'SAA with CME'!H$17,IF(TAAPortfolioPerformance!F20>TAAPortfolioPerformance!$B$4,"",'Index Returns'!G4*TAA!H$24)) -> 0.00068646035 | H20: =IF(G20="","",SUM(B20:G20)) -> -0.0032709632 | I20: =IF(G20="","",(MIN(H20-$B$12,0)^2)) -> 0.00071668447
A21: 43220 | B21: =IF(A21<=$B$3,'Index Returns'!B5*'SAA with CME'!C$17,IF(TAAPortfolioPerformance!A21>TAAPortfolioPerformance!$B$4,"",'Index Returns'!B5*TAA!C$24)) -> -0.005634655 | C21: =IF(B21<=$B$3,'Index Returns'!C5*'SAA with CME'!D$17,IF(TAAPortfolioPerformance!B21>TAAPortfolioPerformance!$B$4,"",'Index Returns'!C5*TAA!D$24)) -> 0.00065936006 | D21: =IF(C21<=$B$3,'Index Returns'!D5*'SAA with CME'!E$17,IF(TAAPortfolioPerformance!C21>TAAPortfolioPerformance!$B$4,"",'Index Returns'!D5*TAA!E$24)) -> 0.0011238748 | E21: =IF(D21<=$B$3,'Index Returns'!E5*'SAA with CME'!F$17,IF(TAAPortfolioPerformance!D21>TAAPortfolioPerformance!$B$4,"",'Index Returns'!E5*TAA!F$24)) -> 0.0018774701 | F21: =IF(E21<=$B$3,'Index Returns'!F5*'SAA with CME'!G$17,IF(TAAPortfolioPerformance!E21>TAAPortfolioPerformance!$B$4,"",'Index Returns'!F5*TAA!G$24)) -> 5.5783422e-05 | G21: =IF(F21<=$B$3,'Index Returns'!G5*'SAA with CME'!H$17,IF(TAAPortfolioPerformance!F21>TAAPortfolioPerformance!$B$4,"",'Index Returns'!G5*TAA!H$24)) -> 0.0010842502 | H21: =IF(G21="","",SUM(B21:G21)) -> -0.00083391642 | I21: =IF(G21="","",(MIN(H21-$B$12,0)^2)) -> 0.00059213949
A22: 43251 | B22: =IF(A22<=$B$3,'Index Returns'!B6*'SAA with CME'!C$17,IF(TAAPortfolioPerformance!A22>TAAPortfolioPerformance!$B$4,"",'Index Returns'!B6*TAA!C$24)) -> 0.0065678023 | C22: =IF(B22<=$B$3,'Index Returns'!C6*'SAA with CME'!D$17,IF(TAAPortfolioPerformance!B22>TAAPortfolioPerformance!$B$4,"",'Index Returns'!C6*TAA!D$24)) -> 0.00066551801 | D22: =IF(C22<=$B$3,'Index Returns'!D6*'SAA with CME'!E$17,IF(TAAPortfolioPerformance!C22>TAAPortfolioPerformance!$B$4,"",'Index Returns'!D6*TAA!E$24)) -> 0.0011245945 | E22: =IF(D22<=$B$3,'Index Returns'!E6*'SAA with CME'!F$17,IF(TAAPortfolioPerformance!D22>TAAPortfolioPerformance!$B$4,"",'Index Returns'!E6*TAA!F$24)) -> 0.0075804864 | F22: =IF(E22<=$B$3,'Index Returns'!F6*'SAA with CME'!G$17,IF(TAAPortfolioPerformance!E22>TAAPortfolioPerformance!$B$4,"",'Index Returns'!F6*TAA!G$24)) -> -0.00076891471 | G22: =IF(F22<=$B$3,'Index Returns'!G6*'SAA with CME'!H$17,IF(TAAPortfolioPerformance!F22>TAAPortfolioPerformance!$B$4,"",'Index Returns'!G6*TAA!H$24)) -> 0.0021958016 | H22: =IF(G22="","",SUM(B22:G22)) -> 0.017365288 | I22: =IF(G22="","",(MIN(H22-$B$12,0)^2)) -> 3.763469e-05
A23: 43280 | B23: =IF(A23<=$B$3,'Index Returns'!B7*'SAA with CME'!C$17,IF(TAAPortfolioPerformance!A23>TAAPortfolioPerformance!$B$4,"",'Index Returns'!B7*TAA!C$24)) -> 0.0074717445 | C23: =IF(B23<=$B$3,'Index Returns'!C7*'SAA with CME'!D$17,IF(TAAPortfolioPerformance!B23>TAAPortfolioPerformance!$B$4,"",'Index Returns'!C7*TAA!D$24)) -> -0.0021363402 | D23: =IF(C23<=$B$3,'Index Returns'!D7*'SAA with CME'!E$17,IF(TAAPortfolioPerformance!C23>TAAPortfolioPerformance!$B$4,"",'Index Returns'!D7*TAA!E$24)) -> -0.0036375457 | E23: =IF(D23<=$B$3,'Index Returns'!E7*'SAA with CME'!F$17,IF(TAAPortfolioPerformance!D23>TAAPortfolioPerformance!$B$4,"",'Index Returns'!E7*TAA!F$24)) -> -0.0043998962 | F23: =IF(E23<=$B$3,'Index Returns'!F7*'SAA with CME'!G$17,IF(TAAPortfolioPerformance!E23>TAAPortfolioPerformance!$B$4,"",'Index Returns'!F7*TAA!G$24)) -> 0.00011626139 | G23: =IF(F23<=$B$3,'Index Returns'!G7*'SAA with CME'!H$17,IF(TAAPortfolioPerformance!F23>TAAPortfolioPerformance!$B$4,"",'Index Returns'!G7*TAA!H$24)) -> 0.0025790931 | H23: =IF(G23="","",SUM(B23:G23)) -> -6.6831488e-06 | I23: =IF(G23="","",(MIN(H23-$B$12,0)^2)) -> 0.00055256415
A24: 43312 | B24: =IF(A24<=$B$3,'Index Returns'!B8*'SAA with CME'!C$17,IF(TAAPortfolioPerformance!A24>TAAPortfolioPerformance!$B$4,"",'Index Returns'!B8*TAA!C$24)) -> 0.0041914921 | C24: =IF(B24<=$B$3,'Index Returns'!C8*'SAA with CME'!D$17,IF(TAAPortfolioPerformance!B24>TAAPortfolioPerformance!$B$4,"",'Index Returns'!C8*TAA!D$24)) -> -0.0015943986 | D24: =IF(C24<=$B$3,'Index Returns'!D8*'SAA with CME'!E$17,IF(TAAPortfolioPerformance!C24>TAAPortfolioPerformance!$B$4,"",'Index Returns'!D8*TAA!E$24)) -> -0.002763261 | E24: =IF(D24<=$B$3,'Index Returns'!E8*'SAA with CME'!F$17,IF(TAAPortfolioPerformance!D24>TAAPortfolioPerformance!$B$4,"",'Index Returns'!E8*TAA!F$24)) -> -0.0016026638 | F24: =IF(E24<=$B$3,'Index Returns'!F8*'SAA with CME'!G$17,IF(TAAPortfolioPerformance!E24>TAAPortfolioPerformance!$B$4,"",'Index Returns'!F8*TAA!G$24)) -> 0.00065594835 | G24: =IF(F24<=$B$3,'Index Returns'!G8*'SAA with CME'!H$17,IF(TAAPortfolioPerformance!F24>TAAPortfolioPerformance!$B$4,"",'Index Returns'!G8*TAA!H$24)) -> 0.0016301113 | H24: =IF(G24="","",SUM(B24:G24)) -> 0.00051722835 | I24: =IF(G24="","",(MIN(H24-$B$12,0)^2)) -> 0.00052820779
A25: 43343 | B25: =IF(A25<=$B$3,'Index Returns'!B9*'SAA with CME'!C$17,IF(TAAPortfolioPerformance!A25>TAAPortfolioPerformance!$B$4,"",'Index Returns'!B9*TAA!C$24)) -> 0.0070728602 | C25: =IF(B25<=$B$3,'Index Returns'!C9*'SAA with CME'!D$17,IF(TAAPortfolioPerformance!B25>TAAPortfolioPerformance!$B$4,"",'Index Returns'!C9*TAA!D$24)) -> -0.00059675165 | D25: =IF(C25<=$B$3,'Index Returns'!D9*'SAA with CME'!E$17,IF(TAAPortfolioPerformance!C25>TAAPortfolioPerformance!$B$4,"",'Index Returns'!D9*TAA!E$24)) -> -0.0010215458 | E25: =IF(D25<=$B$3,'Index Returns'!E9*'SAA with CME'!F$17,IF(TAAPortfolioPerformance!D25>TAAPortfolioPerformance!$B$4,"",'Index Returns'!E9*TAA!F$24)) -> 5.6708813e-06 | F25: =IF(E25<=$B$3,'Index Returns'!F9*'SAA with CME'!G$17,IF(TAAPortfolioPerformance!E25>TAAPortfolioPerformance!$B$4,"",'Index Returns'!F9*TAA!G$24)) -> 0.0006483612 | G25: =IF(F25<=$B$3,'Index Returns'!G9*'SAA with CME'!H$17,IF(TAAPortfolioPerformance!F25>TAAPortfolioPerformance!$B$4,"",'Index Returns'!G9*TAA!H$24)) -> 0.0013213227 | H25: =IF(G25="","",SUM(B25:G25)) -> 0.0074299174 | I25: =IF(G25="","",(MIN(H25-$B$12,0)^2)) -> 0.00025824755
A26: 43371 | B26: =IF(A26<=$B$3,'Index Returns'!B10*'SAA with CME'!C$17,IF(TAAPortfolioPerformance!A26>TAAPortfolioPerformance!$B$4,"",'Index Returns'!B10*TAA!C$24)) -> 0.0047076171 | C26: =IF(B26<=$B$3,'Index Returns'!C10*'SAA with CME'!D$17,IF(TAAPortfolioPerformance!B26>TAAPortfolioPerformance!$B$4,"",'Index Returns'!C10*TAA!D$24)) -> -0.00031860775 | D26: =IF(C26<=$B$3,'Index Returns'!D10*'SAA with CME'!E$17,IF(TAAPortfolioPerformance!C26>TAAPortfolioPerformance!$B$4,"",'Index Returns'!D10*TAA!E$24)) -> -0.00054617438 | E26: =IF(D26<=$B$3,'Index Returns'!E10*'SAA with CME'!F$17,IF(TAAPortfolioPerformance!D26>TAAPortfolioPerformance!$B$4,"",'Index Returns'!E10*TAA!F$24)) -> 0.00795686 | F26: =IF(E26<=$B$3,'Index Returns'!F10*'SAA with CME'!G$17,IF(TAAPortfolioPerformance!E26>TAAPortfolioPerformance!$B$4,"",'Index Returns'!F10*TAA!G$24)) -> -0.00032318034 | G26: =IF(F26<=$B$3,'Index Returns'!G10*'SAA with CME'!H$17,IF(TAAPortfolioPerformance!F26>TAAPortfolioPerformance!$B$4,"",'Index Returns'!G10*TAA!H$24)) -> -0.00058463042 | H26: =IF(G26="","",SUM(B26:G26)) -> 0.010891884 | I26: =IF(G26="","",(MIN(H26-$B$12,0)^2)) -> 0.00015896458
A27: 43404 | B27: =IF(A27<=$B$3,'Index Returns'!B11*'SAA with CME'!C$17,IF(TAAPortfolioPerformance!A27>TAAPortfolioPerformance!$B$4,"",'Index Returns'!B11*TAA!C$24)) -> -0.015409129 | C27: =IF(B27<=$B$3,'Index Returns'!C11*'SAA with CME'!D$17,IF(TAAPortfolioPerformance!B27>TAAPortfolioPerformance!$B$4,"",'Index Returns'!C11*TAA!D$24)) -> -0.0050317546 | D27: =IF(C27<=$B$3,'Index Returns'!D11*'SAA with CME'!E$17,IF(TAAPortfolioPerformance!C27>TAAPortfolioPerformance!$B$4,"",'Index Returns'!D11*TAA!E$24)) -> -0.0085667173 | E27: =IF(D27<=$B$3,'Index Returns'!E11*'SAA with CME'!F$17,IF(TAAPortfolioPerformance!D27>TAAPortfolioPerformance!$B$4,"",'Index Returns'!E11*TAA!F$24)) -> 0.0097588616 | F27: =IF(E27<=$B$3,'Index Returns'!F11*'SAA with CME'!G$17,IF(TAAPortfolioPerformance!E27>TAAPortfolioPerformance!$B$4,"",'Index Returns'!F11*TAA!G$24)) -> -0.00080948278 | G27: =IF(F27<=$B$3,'Index Returns'!G11*'SAA with CME'!H$17,IF(TAAPortfolioPerformance!F27>TAAPortfolioPerformance!$B$4,"",'Index Returns'!G11*TAA!H$24)) -> -0.0037030481 | H27: =IF(G27="","",SUM(B27:G27)) -> -0.023761271 | I27: =IF(G27="","",(MIN(H27-$B$12,0)^2)) -> 0.0022336277
A28: 43434 | B28: =IF(A28<=$B$3,'Index Returns'!B12*'SAA with CME'!C$17,IF(TAAPortfolioPerformance!A28>TAAPortfolioPerformance!$B$4,"",'Index Returns'!B12*TAA!C$24)) -> -0.0076170774 | C28: =IF(B28<=$B$3,'Index Returns'!C12*'SAA with CME'!D$17,IF(TAAPortfolioPerformance!B28>TAAPortfolioPerformance!$B$4,"",'Index Returns'!C12*TAA!D$24)) -> -0.0024771692 | D28: =IF(C28<=$B$3,'Index Returns'!D12*'SAA with CME'!E$17,IF(TAAPortfolioPerformance!C28>TAAPortfolioPerformance!$B$4,"",'Index Returns'!D12*TAA!E$24)) -> -0.0042811271 | E28: =IF(D28<=$B$3,'Index Returns'!E12*'SAA with CME'!F$17,IF(TAAPortfolioPerformance!D28>TAAPortfolioPerformance!$B$4,"",'Index Returns'!E12*TAA!F$24)) -> -0.002235684 | F28: =IF(E28<=$B$3,'Index Returns'!F12*'SAA with CME'!G$17,IF(TAAPortfolioPerformance!E28>TAAPortfolioPerformance!$B$4,"",'Index Returns'!F12*TAA!G$24)) -> -0.00054872829 | G28: =IF(F28<=$B$3,'Index Returns'!G12*'SAA with CME'!H$17,IF(TAAPortfolioPerformance!F28>TAAPortfolioPerformance!$B$4,"",'Index Returns'!G12*TAA!H$24)) -> 0.0020315233 | H28: =IF(G28="","",SUM(B28:G28)) -> -0.015128263 | I28: =IF(G28="","",(MIN(H28-$B$12,0)^2)) -> 0.0014921427
A29: 43465 | B29: =IF(A29<=$B$3,'Index Returns'!B13*'SAA with CME'!C$17,IF(TAAPortfolioPerformance!A29>TAAPortfolioPerformance!$B$4,"",'Index Returns'!B13*TAA!C$24)) -> -0.01757714 | C29: =IF(B29<=$B$3,'Index Returns'!C13*'SAA with CME'!D$17,IF(TAAPortfolioPerformance!B29>TAAPortfolioPerformance!$B$4,"",'Index Returns'!C13*TAA!D$24)) -> -0.0048228645 | D29: =IF(C29<=$B$3,'Index Returns'!D13*'SAA with CME'!E$17,IF(TAAPortfolioPerformance!C29>TAAPortfolioPerformance!$B$4,"",'Index Returns'!D13*TAA!E$24)) -> -0.0082692752 | E29: =IF(D29<=$B$3,'Index Returns'!E13*'SAA with CME'!F$17,IF(TAAPortfolioPerformance!D29>TAAPortfolioPerformance!$B$4,"",'Index Returns'!E13*TAA!F$24)) -> -0.018108228 | F29: =IF(E29<=$B$3,'Index Returns'!F13*'SAA with CME'!G$17,IF(TAAPortfolioPerformance!E29>TAAPortfolioPerformance!$B$4,"",'Index Returns'!F13*TAA!G$24)) -> 0.000877795 | G29: =IF(F29<=$B$3,'Index Returns'!G13*'SAA with CME'!H$17,IF(TAAPortfolioPerformance!F29>TAAPortfolioPerformance!$B$4,"",'Index Returns'!G13*TAA!H$24)) -> -0.0018912625 | H29: =IF(G29="","",SUM(B29:G29)) -> -0.049790975 | I29: =IF(G29="","",(MIN(H29-$B$12,0)^2)) -> 0.005371567
... A86: 45198 | B86: =IF(A86<=$B$3,'Index Returns'!B70*'SAA with CME'!C$17,IF(TAAPortfolioPerformance!A86>TAAPortfolioPerformance!$B$4,"",'Index Returns'!B70*TAA!C$24)) | C86: =IF(B86<=$B$3,'Index Returns'!C70*'SAA with CME'!D$17,IF(TAAPortfolioPerformance!B86>TAAPortfolioPerformance!$B$4,"",'Index Returns'!C70*TAA!D$24)) | D86: =IF(C86<=$B$3,'Index Returns'!D70*'SAA with CME'!E$17,IF(TAAPortfolioPerformance!C86>TAAPortfolioPerformance!$B$4,"",'Index Returns'!D70*TAA!E$24)) | E86: =IF(D86<=$B$3,'Index Returns'!E70*'SAA with CME'!F$17,IF(TAAPortfolioPerformance!D86>TAAPortfolioPerformance!$B$4,"",'Index Returns'!E70*TAA!F$24)) | F86: =IF(E86<=$B$3,'Index Returns'!F70*'SAA with CME'!G$17,IF(TAAPortfolioPerformance!E86>TAAPortfolioPerformance!$B$4,"",'Index Returns'!F70*TAA!G$24)) | G86: =IF(F86<=$B$3,'Index Returns'!G70*'SAA with CME'!H$17,IF(TAAPortfolioPerformance!F86>TAAPortfolioPerformance!$B$4,"",'Index Returns'!G70*TAA!H$24)) | H86: =IF(G86="","",SUM(B86:G86)) | I86: =IF(G86="","",(MIN(H86-$B$12,0)^2))

Sheet CurrencyHedge
B2: Interest Rates
B3: GBP rate | C3: 0.01219
B4: USD rate | C4: 0.02684
B6: Equity Investment
B7: Initial USD Investment | C7: 5000000
B8: Initial GBP Value
B10: Currency Movement
B11: Day | C11: 0 | D11: 1 | E11: 2 | F11: 3 | G11: 4 | H11: 5 | I11: 6 | J11: 7 | K11: 8 | L11: 9 | M11: 10 | N11: 11 | O11: 12 | P11: 13 | Q11: 14 | R11: 15 | S11: 16 | T11: 17 | U11: 18 | V11: 19 | W11: 20 | X11: 21 | Y11: 22 | Z11: 23 | AA11: 24 | AB11: 25 | AC11: 26 | AD11: 27 | AE11: 28 | AF11: 29 | AG11: 30 | AH11: 31 | AI11: 32 | AJ11: 33 | AK11: 34 | AL11: 35 | AM11: 36 | AN11: 37 | AO11: 38 | AP11: 39 | AQ11: 40 | AR11: 41 | AS11: 42 | AT11: 43 | AU11: 44 | AV11: 45 | AW11: 46 | AX11: 47 | AY11: 48 | AZ11: 49 | BA11: 50 | BB11: 51 | BC11: 52 | BD11: 53 | BE11: 54 | BF11: 55 | BG11: 56 | BH11: 57 | BI11: 58 | BJ11: 59 | BK11: 60 | BL11: 61 | BM11: 62 | BN11: 63 | BO11: 64 | BP11: 65 | BQ11: 66 | BR11: 67 | BS11: 68 | BT11: 69 | BU11: 70 | BV11: 71 | BW11: 72 | BX11: 73 | BY11: 74 | BZ11: 75 | CA11: 76 | CB11: 77 | CC11: 78 | CD11: 79 | CE11: 80 | CF11: 81 | CG11: 82 | CH11: 83 | CI11: 84 | CJ11: 85 | CK11: 86 | CL11: 87 | CM11: 88 | CN11: 89 | CO11: 90
B12: Spot USD/GBP | C12: 0.76716532 | D12: 0.766636 | E12: 0.7582076 | F12: 0.75688768 | G12: 0.75786283 | H12: 0.75705958 | I12: 0.76295109 | J12: 0.75769056 | K12: 0.7536931 | L12: 0.75443229 | M12: 0.75244545 | N12: 0.75517293 | O12: 0.74973759 | P12: 0.76481836 | Q12: 0.76045627 | R12: 0.76834422 | S12: 0.76423386 | T12: 0.75930144 | U12: 0.75884049 | V12: 0.75872534 | W12: 0.75746099 | X12: 0.75397723 | Y12: 0.75137125 | Z12: 0.75460308 | AA12: 0.76353363 | AB12: 0.76610741 | AC12: 0.76669478 | AD12: 0.76628352 | AE12: 0.76557954 | AF12: 0.77375426 | AG12: 0.77585538 | AH12: 0.78106694 | AI12: 0.77845244 | AJ12: 0.77567484 | AK12: 0.77790743 | AL12: 0.77255871 | AM12: 0.77208153 | AN12: 0.7732756 | AO12: 0.77249903 | AP12: 0.76704763 | AQ12: 0.76458445 | AR12: 0.76283469 | AS12: 0.76242757 | AT12: 0.76534517 | AU12: 0.75970523 | AV12: 0.7578054 | AW12: 0.76534517 | AX12: 0.76516949 | AY12: 0.77196233 | AZ12: 0.77567484 | BA12: 0.77688005 | BB12: 0.77006006 | BC12: 0.77609624 | BD12: 0.77754451 | BE12: 0.77736318 | BF12: 0.77857365 | BG12: 0.78449831 | BH12: 0.78192196 | BI12: 0.78634898 | BJ12: 0.78265634 | BK12: 0.78597815 | BL12: 0.79189104 | BM12: 0.79321012 | BN12: 0.78492936 | BO12: 0.78406774 | BP12: 0.78746358 | BQ12: 0.79088896 | BR12: 0.79157761 | BS12: 0.78895464 | BT12: 0.78702975 | BU12: 0.79082641 | BV12: 0.79013906 | BW12: 0.79302141 | BX12: 0.79120184 | BY12: 0.79214195 | BZ12: 0.79472304 | CA12: 0.79095151 | CB12: 0.79182833 | CC12: 0.80083287 | CD12: 0.79611496 | CE12: 0.78579287 | CF12: 0.78241139 | CG12: 0.7852992 | CH12: 0.78622533 | CI12: 0.78585462 | CJ12: 0.78437525 | CK12: 0.7817997 | CL12: 0.7797271 | CM12: 0.78449831 | CN12: 0.77960552 | CO12: 0.7791803
B13: Spot GBP/USD
B15: Fund Performance
B16: Day | C16: 0 | D16: 1 | E16: 2 | F16: 3 | G16: 4 | H16: 5 | I16: 6 | J16: 7 | K16: 8 | L16: 9 | M16: 10 | N16: 11 | O16: 12 | P16: 13 | Q16: 14 | R16: 15 | S16: 16 | T16: 17 | U16: 18 | V16: 19 | W16: 20 | X16: 21 | Y16: 22 | Z16: 23 | AA16: 24 | AB16: 25 | AC16: 26 | AD16: 27 | AE16: 28 | AF16: 29 | AG16: 30 | AH16: 31 | AI16: 32 | AJ16: 33 | AK16: 34 | AL16: 35 | AM16: 36 | AN16: 37 | AO16: 38 | AP16: 39 | AQ16: 40 | AR16: 41 | AS16: 42 | AT16: 43 | AU16: 44 | AV16: 45 | AW16: 46 | AX16: 47 | AY16: 48 | AZ16: 49 | BA16: 50 | BB16: 51 | BC16: 52 | BD16: 53 | BE16: 54 | BF16: 55 | BG16: 56 | BH16: 57 | BI16: 58 | BJ16: 59 | BK16: 60 | BL16: 61 | BM16: 62 | BN16: 63 | BO16: 64 | BP16: 65 | BQ16: 66 | BR16: 67 | BS16: 68 | BT16: 69 | BU16: 70 | BV16: 71 | BW16: 72 | BX16: 73 | BY16: 74 | BZ16: 75 | CA16: 76 | CB16: 77 | CC16: 78 | CD16: 79 | CE16: 80 | CF16: 81 | CG16: 82 | CH16: 83 | CI16: 84 | CJ16: 85 | CK16: 86 | CL16: 87 | CM16: 88 | CN16: 89 | CO16: 90
B17: NAV of GBP fund | C17: 100.18556 | D17: 99.819156 | E17: 100.66452 | F17: 100.95566 | G17: 100.69092 | H17: 101.29419 | I17: 101.75152 | J17: 101.44311 | K17: 102.22362 | L17: 102.6985 | M17: 102.76512 | N17: 102.80336 | O17: 103.02523 | P17: 101.80535 | Q17: 99.720557 | R17: 101.43415 | S17: 101.31131 | T17: 100.91074 | U17: 99.170542 | V17: 100.41782 | W17: 101.58897 | X17: 102.40807 | Y17: 103.30679 | Z17: 103.09119 | AA17: 103.44096 | AB17: 103.40249 | AC17: 104.65021 | AD17: 103.6114 | AE17: 104.61711 | AF17: 103.93128 | AG17: 104.63749 | AH17: 104.51943 | AI17: 103.14347 | AJ17: 99.323722 | AK17: 96.623149 | AL17: 95.948631 | AM17: 91.668553 | AN17: 91.572578 | AO17: 94.947708 | AP17: 93.11785 | AQ17: 96.856661 | AR17: 93.299107 | AS17: 92.097947 | AT17: 84.336598 | AU17: 89.466895 | AV17: 85.011376 | AW17: 77.003244 | AX17: 83.324165 | AY17: 73.47898 | AZ17: 78.200813 | BA17: 73.758988 | BB17: 74.839116 | BC17: 70.825745 | BD17: 69.168401 | BE17: 75.871798 | BF17: 76.64404 | BG17: 81.155215 | BH17: 78.717676 | BI17: 81.098725 | BJ17: 79.634697 | BK17: 76.348512 | BL17: 77.70754 | BM17: 77.248187 | BN17: 82.54874 | BO17: 81.969138 | BP17: 85.253516 | BQ17: 85.718784 | BR17: 85.031281 | BS17: 88.095608 | BT17: 85.527695 | BU17: 86.595085 | BV17: 88.395017 | BW17: 87.112047 | BX17: 84.194394 | BY17: 86.680786 | BZ17: 86.519808 | CA17: 87.847322 | CB17: 89.291685 | CC17: 88.045403 | CD17: 90.677576 | CE17: 90.173379 | CF17: 87.679543 | CG17: 87.449956 | CH17: 89.031018 | CI17: 88.242662 | CJ17: 88.953883 | CK17: 90.193198 | CL17: 90.01088 | CM17: 88.155234 | CN17: 87.450661 | CO17: 87.617925
B18: Number of Shares
B20: Value of Investment
B21: Day | C21: 0 | D21: 1 | E21: 2 | F21: 3 | G21: 4 | H21: 5 | I21: 6 | J21: 7 | K21: 8 | L21: 9 | M21: 10 | N21: 11 | O21: 12 | P21: 13 | Q21: 14 | R21: 15 | S21: 16 | T21: 17 | U21: 18 | V21: 19 | W21: 20 | X21: 21 | Y21: 22 | Z21: 23 | AA21: 24 | AB21: 25 | AC21: 26 | AD21: 27 | AE21: 28 | AF21: 29 | AG21: 30 | AH21: 31 | AI21: 32 | AJ21: 33 | AK21: 34 | AL21: 35 | AM21: 36 | AN21: 37 | AO21: 38 | AP21: 39 | AQ21: 40 | AR21: 41 | AS21: 42 | AT21: 43 | AU21: 44 | AV21: 45 | AW21: 46 | AX21: 47 | AY21: 48 | AZ21: 49 | BA21: 50 | BB21: 51 | BC21: 52 | BD21: 53 | BE21: 54 | BF21: 55 | BG21: 56 | BH21: 57 | BI21: 58 | BJ21: 59 | BK21: 60 | BL21: 61 | BM21: 62 | BN21: 63 | BO21: 64 | BP21: 65 | BQ21: 66 | BR21: 67 | BS21: 68 | BT21: 69 | BU21: 70 | BV21: 71 | BW21: 72 | BX21: 73 | BY21: 74 | BZ21: 75 | CA21: 76 | CB21: 77 | CC21: 78 | CD21: 79 | CE21: 80 | CF21: 81 | CG21: 82 | CH21: 83 | CI21: 84 | CJ21: 85 | CK21: 86 | CL21: 87 | CM21: 88 | CN21: 89 | CO21: 90
B22: Value of Investment (GBP)
B23: Value of Investment (USD)
B25: Performance (rebased to 100)
B26: Day | C26: 0 | D26: 1 | E26: 2 | F26: 3 | G26: 4 | H26: 5 | I26: 6 | J26: 7 | K26: 8 | L26: 9 | M26: 10 | N26: 11 | O26: 12 | P26: 13 | Q26: 14 | R26: 15 | S26: 16 | T26: 17 | U26: 18 | V26: 19 | W26: 20 | X26: 21 | Y26: 22 | Z26: 23 | AA26: 24 | AB26: 25 | AC26: 26 | AD26: 27 | AE26: 28 | AF26: 29 | AG26: 30 | AH26: 31 | AI26: 32 | AJ26: 33 | AK26: 34 | AL26: 35 | AM26: 36 | AN26: 37 | AO26: 38 | AP26: 39 | AQ26: 40 | AR26: 41 | AS26: 42 | AT26: 43 | AU26: 44 | AV26: 45 | AW26: 46 | AX26: 47 | AY26: 48 | AZ26: 49 | BA26: 50 | BB26: 51 | BC26: 52 | BD26: 53 | BE26: 54 | BF26: 55 | BG26: 56 | BH26: 57 | BI26: 58 | BJ26: 59 | BK26: 60 | BL26: 61 | BM26: 62 | BN26: 63 | BO26: 64 | BP26: 65 | BQ26: 66 | BR26: 67 | BS26: 68 | BT26: 69 | BU26: 70 | BV26: 71 | BW26: 72 | BX26: 73 | BY26: 74 | BZ26: 75 | CA26: 76 | CB26: 77 | CC26: 78 | CD26: 79 | CE26: 80 | CF26: 81 | CG26: 82 | CH26: 83 | CI26: 84 | CJ26: 85 | CK26: 86 | CL26: 87 | CM26: 88 | CN26: 89 | CO26: 90
B27: Value of Investment (GBP)
B28: Value of Investment (USD)
B46: Hedging With A Future (50% Hedge Ratio)
B48: Contract Details
B49: USD GBP Contract size | C49: 500000
B50: Hedging Ratio | C50: 0.5
B51: No contracts to hedge
B52: Long (+1) / Short (-1) | C52: -1
B54: Hedged Value of Portfolio (USD)
B55: Day | C55: 0 | D55: 1 | E55: 2 | F55: 3 | G55: 4 | H55: 5 | I55: 6 | J55: 7 | K55: 8 | L55: 9 | M55: 10 | N55: 11 | O55: 12 | P55: 13 | Q55: 14 | R55: 15 | S55: 16 | T55: 17 | U55: 18 | V55: 19 | W55: 20 | X55: 21 | Y55: 22 | Z55: 23 | AA55: 24 | AB55: 25 | AC55: 26 | AD55: 27 | AE55: 28 | AF55: 29 | AG55: 30 | AH55: 31 | AI55: 32 | AJ55: 33 | AK55: 34 | AL55: 35 | AM55: 36 | AN55: 37 | AO55: 38 | AP55: 39 | AQ55: 40 | AR55: 41 | AS55: 42 | AT55: 43 | AU55: 44 | AV55: 45 | AW55: 46 | AX55: 47 | AY55: 48 | AZ55: 49 | BA55: 50 | BB55: 51 | BC55: 52 | BD55: 53 | BE55: 54 | BF55: 55 | BG55: 56 | BH55: 57 | BI55: 58 | BJ55: 59 | BK55: 60 | BL55: 61 | BM55: 62 | BN55: 63 | BO55: 64 | BP55: 65 | BQ55: 66 | BR55: 67 | BS55: 68 | BT55: 69 | BU55: 70 | BV55: 71 | BW55: 72 | BX55: 73 | BY55: 74 | BZ55: 75 | CA55: 76 | CB55: 77 | CC55: 78 | CD55: 79 | CE55: 80 | CF55: 81 | CG55: 82 | CH55: 83 | CI55: 84 | CJ55: 85 | CK55: 86 | CL55: 87 | CM55: 88 | CN55: 89 | CO55: 90
B56: Fair Value of Future (Day 90 Delivery)
B57: Cumulative P&L on Contract
B58: Unhedged Value of Portfolio (USD)
B59: Hedged Value of Portfolio (USD)
B61: Performance (rebased to 100)
B62: Day | C62: 0 | D62: 1 | E62: 2 | F62: 3 | G62: 4 | H62: 5 | I62: 6 | J62: 7 | K62: 8 | L62: 9 | M62: 10 | N62: 11 | O62: 12 | P62: 13 | Q62: 14 | R62: 15 | S62: 16 | T62: 17 | U62: 18 | V62: 19 | W62: 20 | X62: 21 | Y62: 22 | Z62: 23 | AA62: 24 | AB62: 25 | AC62: 26 | AD62: 27 | AE62: 28 | AF62: 29 | AG62: 30 | AH62: 31 | AI62: 32 | AJ62: 33 | AK62: 34 | AL62: 35 | AM62: 36 | AN62: 37 | AO62: 38 | AP62: 39 | AQ62: 40 | AR62: 41 | AS62: 42 | AT62: 43 | AU62: 44 | AV62: 45 | AW62: 46 | AX62: 47 | AY62: 48 | AZ62: 49 | BA62: 50 | BB62: 51 | BC62: 52 | BD62: 53 | BE62: 54 | BF62: 55 | BG62: 56 | BH62: 57 | BI62: 58 | BJ62: 59 | BK62: 60 | BL62: 61 | BM62: 62 | BN62: 63 | BO62: 64 | BP62: 65 | BQ62: 66 | BR62: 67 | BS62: 68 | BT62: 69 | BU62: 70 | BV62: 71 | BW62: 72 | BX62: 73 | BY62: 74 | BZ62: 75 | CA62: 76 | CB62: 77 | CC62: 78 | CD62: 79 | CE62: 80 | CF62: 81 | CG62: 82 | CH62: 83 | CI62: 84 | CJ62: 85 | CK62: 86 | CL62: 87 | CM62: 88 | CN62: 89 | CO62: 90
B63: 50% Hedged (USD)
B64: Unhedged (USD)
